KeplerOrbit/KeplerOrbit.py
KeplerOrbit/MathHelpers.py
KeplerOrbit/__init__.py
KeplerOrbit-0.21.dist-info/LICENSE
KeplerOrbit-0.21.dist-info/METADATA
KeplerOrbit-0.21.dist-info/WHEEL
KeplerOrbit-0.21.dist-info/top_level.txt
KeplerOrbit-0.21.dist-info/RECORD
