Metadata-Version: 2.1
Name: KeplerOrbit
Version: 0.21
Summary: Routines for working with Keplerian orbits
Home-page: https://github.com/spencerw/KeplerOrbit
Author: Spencer Wallace
Author-email: scw7@uw.edu
License: New BSD
Platform: UNKNOWN
Classifier: Programming Language :: Python :: 3
Classifier: License :: OSI Approved :: MIT License
Classifier: Operating System :: OS Independent
